lightwave/__init__.py
lightwave/lightwave.py
lightwave-0.23.dist-info/LICENSE
lightwave-0.23.dist-info/METADATA
lightwave-0.23.dist-info/WHEEL
lightwave-0.23.dist-info/top_level.txt
lightwave-0.23.dist-info/RECORD
