Metadata-Version: 2.1
Name: lightwave
Version: 0.23
Summary: Python library to provide a reliable communication link with LightWaveRF lights, switches and TRVs.
Home-page: https://github.com/GeoffAtHome/lightwave
Author: Geoff Soord
Author-email: geoff@soord.org.uk
License: MIT
Keywords: Lightwave,LightwaveRF,Lightwave WiFiLink,Lightwave Link
License-File: LICENSE
